fragrance_api/__init__.py
fragrance_api/core.py
fragrantica_api-0.1.dist-info/METADATA
fragrantica_api-0.1.dist-info/WHEEL
fragrantica_api-0.1.dist-info/top_level.txt
fragrantica_api-0.1.dist-info/RECORD
